{"name":"Website 2 APK Builder","tagline":"Transform your site to an Android App","body":"### Welcome to Website 2 APK Builder   \r\n### Convert your Website to a working Android App. Supports html, php, htm, js, css. Build app from any web server site or from local directory.\r\n\r\n![Website2APK Builder](http://a.fsdn.com/con/app/proj/website2apk/screenshots/Screenshot1.png)   \r\n![Website2APK Builder](http://a.fsdn.com/con/app/proj/website2apk/screenshots/Screenshot2.png)   \r\n![Website2APK Builder](http://a.fsdn.com/con/app/proj/website2apk/screenshots/Screenshot3.png)   \r\n\r\n**Features**\r\n* Build Android Apps easily from your Web Content\r\n* Create Apps in seconds for your Live Website\r\n* Custom icon for your App\r\n* Customised App Name\r\n* Generates Ad-Free Android App\r\n* User Friendly   \r\n\r\nAlso Available at:\r\nhttp://sourceforge.net/projects/website2apk/\r\n\r\nSupport:\r\nMail: website2apkbuilder@gmail.com\r\n\r\nhttps://www.facebook.com/Website2APK\r\n\r\nhttps://twitter.com/WebsiteToAPK","google":"","note":"Don't delete this file! It's used internally to help with page regeneration."}